{
  "indexes": [
    {
      "collectionGroup": "labRequests",
      "queryScope": "COLLECTION",
      "fields": [
        { "fieldPath": "status", "order": "ASCENDING" },
        { "fieldPath": "createdAt", "order": "DESCENDING" }
      ]
    },
    {
      "collectionGroup": "queue",
      "queryScope": "COLLECTION",
      "fields": [
        { "fieldPath": "status", "order": "ASCENDING" },
        { "fieldPath": "createdAt", "order": "ASCENDING" }
      ]
    },
    {
      "collectionGroup": "prescriptions",
      "queryScope": "COLLECTION",
      "fields": [
        { "fieldPath": "status", "order": "ASCENDING" },
        { "fieldPath": "date", "order": "DESCENDING" }
      ]
    },
    {
      "collectionGroup": "appointments",
      "queryScope": "COLLECTION",
      "fields": [
        { "fieldPath": "patientId", "order": "ASCENDING" },
        { "fieldPath": "status", "order": "ASCENDING" },
        { "fieldPath": "date", "order": "DESCENDING" }
      ]
    },
    {
      "collectionGroup": "inventory",
      "queryScope": "COLLECTION",
      "fields": [
        { "fieldPath": "quantity", "order": "ASCENDING" },
        { "fieldPath": "name", "order": "ASCENDING" }
      ]
    },
    {
      "collectionGroup": "labResults",
      "queryScope": "COLLECTION",
      "fields": [
        { "fieldPath": "requestId", "order": "ASCENDING" },
        { "fieldPath": "createdAt", "order": "DESCENDING" }
      ]
    }
  ],
  "fieldOverrides": []
}

